resistics_readers/__init__.py
resistics_readers/lemi/__init__.py
resistics_readers/lemi/b423.py
resistics_readers/lemi/b423e.py
resistics_readers/metronix/__init__.py
resistics_readers/metronix/ats.py
resistics_readers/metronix/calibration.py
resistics_readers/miniseed/__init__.py
resistics_readers/miniseed/mseed.py
resistics_readers/multifile.py
resistics_readers/phoenix/__init__.py
resistics_readers/phoenix/headers.py
resistics_readers/phoenix/mtu5.py
resistics_readers/spam/__init__.py
resistics_readers/spam/calibration.py
resistics_readers/spam/spam.py
resistics_readers-0.1.3.dist-info/WHEEL
resistics_readers-0.1.3.dist-info/METADATA
resistics_readers-0.1.3.dist-info/RECORD
